arithmetical_date_range.py
arithmetical_date_range-0.2.0.dist-info/WHEEL
arithmetical_date_range-0.2.0.dist-info/METADATA
arithmetical_date_range-0.2.0.dist-info/RECORD
