Metadata-Version: 2.1
Name: arithmetical-date-range
Version: 0.2.0
Summary: Add an subtract date ranges
Author: Your Name
Author-email: you@example.com
Requires-Python: >=3.8,<4.0
Classifier: Programming Language :: Python :: 3
Classifier: Programming Language :: Python :: 3.8
Classifier: Programming Language :: Python :: 3.9
